Metadata-Version: 2.1
Name: csv2json.py
Version: 1.1
Summary: A utility to convert CSVs to JSON
Home-page: https://github.com/Sonictherocketman/csv2json
Author: Brian Schrader
Author-email: brian@brianschrader.com
License: UNKNOWN
Project-URL: Bug Tracker, https://github.com/Sonictherocketman/csv2json/issues
Platform: UNKNOWN
Classifier: Programming Language :: Python :: 3
Classifier: License :: OSI Approved :: MIT License
Classifier: Operating System :: OS Independent
Requires-Python: >=3.7
License-File: LICENSE
